delta/__init__.py
delta/adaptive.py
delta/analysis.py
delta/ast_python.py
delta/bpe_discovery.py
delta/compressor.py
delta/config.py
delta/config_helpers.py
delta/corpus.py
delta/dictionary.py
delta/dictionary_store.py
delta/discovery.py
delta/discovery_parallel.py
delta/discovery_sa.py
delta/domain.py
delta/embedding_cache.py
delta/embeddings.py
delta/engine.py
delta/fuzzy.py
delta/metrics.py
delta/metrics_writer.py
delta/offline_pipeline.py
delta/pattern_cache.py
delta/pattern_importance.py
delta/patterns.py
delta/preprocess.py
delta/quality_alerts.py
delta/quality_export.py
delta/quality_monitor.py
delta/quality_predictor.py
delta/selection.py
delta/selection_ilp.py
delta/selection_semantic.py
delta/sequence.py
delta/serialization.py
delta/static_dict_builder.py
delta/static_dict_io.py
delta/static_dicts.py
delta/streaming.py
delta/subsumption.py
delta/suffix_array.py
delta/suffix_array_fast.py
delta/swap.py
delta/template_discovery.py
delta/template_serialization.py
delta/template_types.py
delta/tokenizer.py
delta/training.py
delta/types.py
delta/utils.py
delta/validation.py
delta/vocab.py
delta/mcp/__init__.py
delta/mcp/__main__.py
delta/mcp/config.py
delta/mcp/metrics.py
delta/mcp/server.py
delta/mcp/tools.py
delta_ltsc-0.3.1.dist-info/licenses/LICENSE
delta_ltsc-0.3.1.dist-info/METADATA
delta_ltsc-0.3.1.dist-info/WHEEL
delta_ltsc-0.3.1.dist-info/entry_points.txt
delta_ltsc-0.3.1.dist-info/top_level.txt
delta_ltsc-0.3.1.dist-info/RECORD
