Metadata-Version: 2.4
Name: delta-ltsc
Version: 0.3.1
Summary: Lossless token sequence compression for large language models
Author: Nikhil Srivastava, Omansh Bainsla, Sahil Chatiwala
Author-email: Triage Sec <nicks@triage-sec.com>
License-Expression: MIT
Keywords: llm,compression,tokens,context,inference,transformers
Classifier: Development Status :: 4 - Beta
Classifier: Intended Audience :: Developers
Classifier: Intended Audience :: Science/Research
Classifier: Programming Language :: Python :: 3
Classifier: Programming Language :: Python :: 3.10
Classifier: Programming Language :: Python :: 3.11
Classifier: Programming Language :: Python :: 3.12
Classifier: Topic :: Scientific/Engineering :: Artificial Intelligence
Classifier: Topic :: Text Processing :: General
Classifier: Typing :: Typed
Requires-Python: >=3.10
License-File: LICENSE
Requires-Dist: numpy>=1.24.0
Requires-Dist: tiktoken>=0.5.0
Requires-Dist: pyyaml>=6.0
Requires-Dist: click>=8.0
Requires-Dist: tqdm>=4.65
Provides-Extra: tokenizers
Requires-Dist: transformers>=4.35.0; extra == "tokenizers"
Requires-Dist: sentencepiece>=0.1.99; extra == "tokenizers"
Provides-Extra: embeddings
Requires-Dist: sentence-transformers>=2.2.0; extra == "embeddings"
Requires-Dist: torch>=2.0.0; extra == "embeddings"
Requires-Dist: openai>=1.0.0; extra == "embeddings"
Requires-Dist: httpx>=0.25.0; extra == "embeddings"
Requires-Dist: voyageai>=0.1.4; extra == "embeddings"
Requires-Dist: cohere>=4.30; extra == "embeddings"
Requires-Dist: zstandard>=0.22.0; extra == "embeddings"
Requires-Dist: redis>=5.0.0; extra == "embeddings"
Provides-Extra: analysis
Requires-Dist: delta-ltsc[embeddings]; extra == "analysis"
Requires-Dist: scikit-learn>=1.3.0; extra == "analysis"
Requires-Dist: scipy>=1.11.0; extra == "analysis"
Requires-Dist: matplotlib>=3.7.0; extra == "analysis"
Requires-Dist: pandas>=2.0.0; extra == "analysis"
Provides-Extra: training
Requires-Dist: delta-ltsc[tokenizers]; extra == "training"
Requires-Dist: datasets>=2.14.0; extra == "training"
Requires-Dist: accelerate>=0.24.0; extra == "training"
Requires-Dist: peft>=0.6.0; extra == "training"
Requires-Dist: wandb>=0.15.0; extra == "training"
Provides-Extra: dev
Requires-Dist: delta-ltsc[analysis,training]; extra == "dev"
Requires-Dist: pytest>=7.4; extra == "dev"
Requires-Dist: pytest-cov>=4.1.0; extra == "dev"
Requires-Dist: pytest-benchmark>=4.0.0; extra == "dev"
Requires-Dist: hypothesis>=6.88.0; extra == "dev"
Requires-Dist: mypy>=1.6.0; extra == "dev"
Requires-Dist: ruff==0.14.14; extra == "dev"
Requires-Dist: pre-commit>=3.5.0; extra == "dev"
Provides-Extra: all
Requires-Dist: delta-ltsc[analysis,embeddings,tokenizers,training]; extra == "all"
Provides-Extra: mcp
Requires-Dist: mcp>=1.0.0; extra == "mcp"
Dynamic: license-file
